txhyy/Test.py
txhyy/__init__.py
txhyy/__version__.py
txhyy/_hash.pyd
txhyy/_p.py
txhyy/_txhyy.pyd
txhyy/count.pyd
txhyy/dialog.py
txhyy/file.pyd
txhyy/main.pyi
txhyy/pyc.py
txhyy/reg.py
txhyy/setting.pyd
txhyy/txapktool.py
txhyy/txbook.py
txhyy/txfz.py
txhyy/txhyy_code.pyd
txhyy/txhyy_code.pyi
txhyy/txmodels.py
txhyy/txpip.py
txhyy/txstr.py
txhyy/txtree.py
txhyy/txzhushi.py
txhyy/zhushi.py
txhyy/Image/__init__.py
txhyy/Image/bmp.py
txhyy/Image/jpeg.py
txhyy/Image/jpg.py
txhyy/Image/png.py
txhyy/Image/webp.py
txhyy/Video/__init__.py
txhyy/Video/avi.py
txhyy/Video/mkv.py
txhyy/Video/mov.py
txhyy/Video/mp4.py
txhyy/txhyy0a/__init__.py
txhyy/txhyy0a/setup.py
txhyy/txhyy0a/txhyy/__init__.py
txhyy/txhyy0a/txhyy/__version__.py
txhyy/txhyy0a/txhyy/_p.py
txhyy/txhyy0a/txhyy/_txhyy.py
txhyy/txhyy0a/txhyy/dialog.py
txhyy/txhyy0a/txhyy/main.pyi
txhyy/txhyy0a/txhyy/pyc.py
txhyy/txhyy0a/txhyy/reg.py
txhyy/txhyy0a/txhyy/setting.py
txhyy/txhyy0a/txhyy/txbook.py
txhyy/txhyy0a/txhyy/txfz.py
txhyy/txhyy0a/txhyy/txtree.py
txhyy/txhyy0a/txhyy/txzhushi.py
txhyy/txhyy0a/txhyy/zhushi.py
txhyy/txhyy0a/txhyy/Image/__init__.py
txhyy/txhyy0a/txhyy/Image/bmp.py
txhyy/txhyy0a/txhyy/Image/jpeg.py
txhyy/txhyy0a/txhyy/Image/jpg.py
txhyy/txhyy0a/txhyy/Image/png.py
txhyy/txhyy0a/txhyy/Image/webp.py
txhyy/txhyy0a/txhyy/Video/__init__.py
txhyy/txhyy0a/txhyy/Video/avi.py
txhyy/txhyy0a/txhyy/Video/mkv.py
txhyy/txhyy0a/txhyy/Video/mov.py
txhyy/txhyy0a/txhyy/Video/mp4.py
txhyy/txhyy1/__init__.py
txhyy/txhyy1/setup.py
txhyy/txhyy1/txhyy/__init__.py
txhyy/txhyy1/txhyy/__version__.py
txhyy/txhyy1/txhyy/dialog.py
txhyy/txhyy1/txhyy/pyc.py
txhyy/txhyy1/txhyy/reg.py
txhyy/txhyy1/txhyy/zhushi.py
txhyy/txhyy1/txhyy/Image/__init__.py
txhyy/txhyy1/txhyy/Image/bmp.py
txhyy/txhyy1/txhyy/Image/jpeg.py
txhyy/txhyy1/txhyy/Image/jpegs.py
txhyy/txhyy1/txhyy/Image/jpg.py
txhyy/txhyy1/txhyy/Image/png.py
txhyy/txhyy1/txhyy/Image/webp.py
txhyy/txhyy1/txhyy/Video/__init__.py
txhyy/txhyy1/txhyy/Video/avi.py
txhyy-0.1.8.dist-info/LICENSE.txt
txhyy-0.1.8.dist-info/METADATA
txhyy-0.1.8.dist-info/WHEEL
txhyy-0.1.8.dist-info/entry_points.txt
txhyy-0.1.8.dist-info/top_level.txt
txhyy-0.1.8.dist-info/RECORD
