Metadata-Version: 2.2
Name: txhyy
Version: 0.1.8
Summary: txhyy
Author: huang yi yi
Author-email: 363766687@qq.com
Requires-Python: >=3.6
License-File: LICENSE.txt
Requires-Dist: PyQt6
Requires-Dist: moviepy==1.0.3
Requires-Dist: uncompyle6
Requires-Dist: pysrt
Requires-Dist: pillow
Requires-Dist: fonttools
Requires-Dist: wmi
Requires-Dist: pywin32
Requires-Dist: cryptography
Requires-Dist: codinghou
Requires-Dist: rich
Requires-Dist: tqdm
Requires-Dist: mpmath
Requires-Dist: plyer
Requires-Dist: psutil
Requires-Dist: pynvml
Requires-Dist: opencv-python
Dynamic: author
Dynamic: author-email
Dynamic: description
Dynamic: requires-dist
Dynamic: requires-python
Dynamic: summary
